Metadata-Version: 1.0
Name: githost
Version: 2022.4.21.0
Summary: A command-line interface to various git repository hosting services
Home-page: https://github.com/erjoalgo/githost
Author: Ernesto Alfonso
Author-email: erjoalgo@gmail.com
License: GPLv3
Platform: UNKNOWN
